electron_search/__init__.py
electron_search/search.py
electron_search-1.3.1.dist-info/LICENSE.txt
electron_search-1.3.1.dist-info/METADATA
electron_search-1.3.1.dist-info/WHEEL
electron_search-1.3.1.dist-info/top_level.txt
electron_search-1.3.1.dist-info/RECORD
