Metadata-Version: 2.1
Name: electron_search
Version: 1.3.1
Summary: Search for Electron-based applications
Home-page: https://github.com/ripeda/Electron-Search
Author: RIPEDA Consulting
Author-email: info@ripeda.com
License: 3-clause BSD License
Requires-Python: >=3.6
License-File: LICENSE.txt
